lute_thai_parser/__init__.py
lute_thai_parser/parser.py
lute3_thai-0.0.3.dist-info/entry_points.txt
lute3_thai-0.0.3.dist-info/WHEEL
lute3_thai-0.0.3.dist-info/METADATA
lute3_thai-0.0.3.dist-info/RECORD
