Metadata-Version: 2.1
Name: lute3-thai
Version: 0.0.3
Summary: Learning Using Texts - Thai Parser
Author: Justin Dom
Requires-Python: >=3.8
Requires-Dist: lute3>=3.4.2
Requires-Dist: pythainlp==5.0.4
